up_down_counter.v
`timescale 1ns / 1ps
module up_down_counter (
    input clk,
    input reset,
    input load,
    input up,
    input down,
    input [3:0] data_in,
    output reg [3:0] count
);

always @(posedge clk or posedge reset) begin
    if (reset) begin
        count <= 4'b0000;
    end
    else if (load) begin
        count <= data_in;
    end
    else if (up) begin
        count <= count + 1;
    end
    else if (down) begin
        count <= count - 1;
    end
end

endmodule

tb_up_down_counter.v
`timescale 1ns / 1ps
module tb_up_down_counter;

    reg clk;
    reg reset;
    reg load;
    reg up;
    reg down;
    reg [3:0] data_in;
    wire [3:0] count;

    // Unit Under Test (UUT) for instantiation of module up_down_counter
    up_down_counter uut (
        .clk(clk),
        .reset(reset),
        .load(load),
        .up(up),
        .down(down),
        .data_in(data_in),
        .count(count)
    );

    // Clock generation
    always #5 clk = ~clk;

    initial begin
        // Dump file for generating waveform (gtkwave)
        $dumpfile("up_down_counter_waveform.vcd"); // VCD file
        $dumpvars(0, tb_up_down_counter); // Dumps all variables in this module
        
        // Initialize inputs
        clk = 0;
        reset = 0;
        load = 0;
        up = 0;
        down = 0;
        data_in = 4'b0000;

        // Applying reset
        reset = 1;
        #10;
        reset = 0;

        // Testing Load functionality
        data_in = 4'b0010;
        load = 1;
        #10;
        load = 0;

        // Testing Up counting
        up = 1;
        #20;
        up = 0;

        // Testing Down counting
        down = 1;
        #20;
        down = 0;
	    #10;

	    // Testing priority of reset, Load, Up and Down
	    reset = 1;
	    data_in = 4'b0110;
	    load = 1;
	    up = 1;
	    down = 1;
	    #20;
	
	    reset=0;
	    #20

	    load=0;
	    #160

	    up=0;
	    #40

	    down=0;
	    #20 

        // Finish simulation
        #10;
        $finish;
    end
endmodule

//Conditions tested

//reset : 1 0 0 0 0 1 0 0 0 0
//load  : 0 1 0 0 0 1 1 0 0 0
//up    : 0 0 1 0 0 1 1 1 0 0
//down  : 0 0 0 1 0 1 1 1 1 0

//data_in input is changed as well in-between to test the load functionality

up_down_counter_waveform.vcd
$date
	Wed Oct 09 18:12:08 2024
$end
$version
	Icarus Verilog
$end
$timescale
	1ps
$end
$scope module tb_up_down_counter $end
$var wire 4 ! count [3:0] $end
$var reg 1 " clk $end
$var reg 4 # data_in [3:0] $end
$var reg 1 $ down $end
$var reg 1 % load $end
$var reg 1 & reset $end
$var reg 1 ' up $end
$scope module uut $end
$var wire 1 ( clk $end
$var wire 4 ) data_in [3:0] $end
$var wire 1 * down $end
$var wire 1 + load $end
$var wire 1 , reset $end
$var wire 1 - up $end
$var reg 4 . count [3:0] $end
$upscope $end
$upscope $end
$enddefinitions $end
#0
$dumpvars
b0 .
0-
1,
0+
0*
b0 )
0(
0'
1&
0%
0$
b0 #
0"
b0 !
$end
#5000
1"
1(
#10000
0"
0(
1%
1+
b10 #
b10 )
0&
0,
#15000
b10 .
b10 !
1"
1(
#20000
0"
0(
1'
1-
0%
0+
#25000
b11 .
b11 !
1"
1(
#30000
0"
0(
#35000
b100 .
b100 !
1"
1(
#40000
0"
0(
1$
1*
0'
0-
#45000
b11 .
b11 !
1"
1(
#50000
0"
0(
#55000
b10 .
b10 !
1"
1(
#60000
0"
0(
0$
0*
#65000
1"
1(
#70000
b0 .
b0 !
0"
0(
1$
1*
1'
1-
1%
1+
b110 #
b110 )
1&
1,
#75000
1"
1(
#80000
0"
0(
#85000
1"
1(
#90000
0"
0(
0&
0,
#95000
b110 .
b110 !
1"
1(
#100000
0"
0(
#105000
1"
1(
#110000
0"
0(
0%
0+
#115000
b111 .
b111 !
1"
1(
#120000
0"
0(
#125000
b1000 .
b1000 !
1"
1(
#130000
0"
0(
#135000
b1001 .
b1001 !
1"
1(
#140000
0"
0(
#145000
b1010 .
b1010 !
1"
1(
#150000
0"
0(
#155000
b1011 .
b1011 !
1"
1(
#160000
0"
0(
#165000
b1100 .
b1100 !
1"
1(
#170000
0"
0(
#175000
b1101 .
b1101 !
1"
1(
#180000
0"
0(
#185000
b1110 .
b1110 !
1"
1(
#190000
0"
0(
#195000
b1111 .
b1111 !
1"
1(
#200000
0"
0(
#205000
b0 .
b0 !
1"
1(
#210000
0"
0(
#215000
b1 .
b1 !
1"
1(
#220000
0"
0(
#225000
b10 .
b10 !
1"
1(
#230000
0"
0(
#235000
b11 .
b11 !
1"
1(
#240000
0"
0(
#245000
b100 .
b100 !
1"
1(
#250000
0"
0(
#255000
b101 .
b101 !
1"
1(
#260000
0"
0(
#265000
b110 .
b110 !
1"
1(
#270000
0"
0(
0'
0-
#275000
b101 .
b101 !
1"
1(
#280000
0"
0(
#285000
b100 .
b100 !
1"
1(
#290000
0"
0(
#295000
b11 .
b11 !
1"
1(
#300000
0"
0(
#305000
b10 .
b10 !
1"
1(
#310000
0"
0(
0$
0*
